bdq/__init__.py
bdq/dag.py
bdq/dataframe.py
bdq/functions.py
bdq/schema.py
bdq/spark_pipeline.py
bdq/spark_ui_logger.py
bdq/statestore.py
bdq-0.1.0.dist-info/LICENSE
bdq-0.1.0.dist-info/METADATA
bdq-0.1.0.dist-info/WHEEL
bdq-0.1.0.dist-info/top_level.txt
bdq-0.1.0.dist-info/RECORD
