Metadata-Version: 2.1
Name: bdq
Version: 0.1.0
Summary: Big Data Quality, a set of tools/function that help you every day assert quality of datasets you have processed or ingested
Author-email: Grzegorz Rusin <grzegorz.rusin@databricks.com>
Project-URL: Homepage, https://github.com/grusin-db/bdq
Project-URL: Bug Tracker, https://github.com/grusin-db/bdq/issues
Classifier: Programming Language :: Python :: 3
Classifier: License :: OSI Approved :: Apache Software License
Classifier: Operating System :: OS Independent
Requires-Python: >=3.8
License-File: LICENSE
